{
  "formatVersion": "1.1",
  "component": {
    "group": "com.ifels.controlflex",
    "module": "controlflex-api",
    "version": "0.8.5",
    "attributes": {
      "org.gradle.status": "release"
    }
  },
  "createdBy": {
    "gradle": {
      "version": "8.8"
    }
  },
  "variants": [
    {
      "name": "apiElements",
      "attributes": {
        "org.gradle.category": "library",
        "org.gradle.dependency.bundling": "external",
        "org.gradle.jvm.version": 17,
        "org.gradle.libraryelements": "jar",
        "org.gradle.usage": "java-api"
      },
      "files": [
        {
          "name": "controlflex-api-0.8.5.jar",
          "url": "controlflex-api-0.8.5.jar",
          "size": 8888,
          "sha512": "43073b6963e2893b7438b7f971c0bd8e8d6e9fbf35a2e0b1149880099dc77c63faa4e6e1b349bc67bc9b3311750d4be5b82f0468eb602633f3059375330aaa3c",
          "sha256": "fae693149c16ae4d63950fe852084c608b8051989d50f125a00bd373794003f5",
          "sha1": "089e57cc291fcfc3ff8c85be4ece66482c1d7d0d",
          "md5": "7b1f56ac03d56dad1ac5cf7ce3a82768"
        }
      ]
    },
    {
      "name": "runtimeElements",
      "attributes": {
        "org.gradle.category": "library",
        "org.gradle.dependency.bundling": "external",
        "org.gradle.jvm.version": 17,
        "org.gradle.libraryelements": "jar",
        "org.gradle.usage": "java-runtime"
      },
      "files": [
        {
          "name": "controlflex-api-0.8.5.jar",
          "url": "controlflex-api-0.8.5.jar",
          "size": 8888,
          "sha512": "43073b6963e2893b7438b7f971c0bd8e8d6e9fbf35a2e0b1149880099dc77c63faa4e6e1b349bc67bc9b3311750d4be5b82f0468eb602633f3059375330aaa3c",
          "sha256": "fae693149c16ae4d63950fe852084c608b8051989d50f125a00bd373794003f5",
          "sha1": "089e57cc291fcfc3ff8c85be4ece66482c1d7d0d",
          "md5": "7b1f56ac03d56dad1ac5cf7ce3a82768"
        }
      ]
    },
    {
      "name": "sourcesElements",
      "attributes": {
        "org.gradle.category": "documentation",
        "org.gradle.dependency.bundling": "external",
        "org.gradle.docstype": "sources",
        "org.gradle.usage": "java-runtime"
      },
      "files": [
        {
          "name": "controlflex-api-0.8.5-sources.jar",
          "url": "controlflex-api-0.8.5-sources.jar",
          "size": 10282,
          "sha512": "02fd3606cc82411f8b01f5deda41aacfb7776bb8f57da650c9075bae29f5784db67cfd92b733265c09a0d9271b6369a192d014ade57ea2fcb5feb5ef1d3cf357",
          "sha256": "ddef02db19b60000d441abfbe006ce75140decb09bd881911f11296273121829",
          "sha1": "cd1c9dc8f90f4a73853437b024d012918b4b391d",
          "md5": "2707abb2f39a12681d9595cec6a86cd2"
        }
      ]
    }
  ]
}
